ksa/ksa.v
module ksa #(parameter N=4)(input [N-1:0] a,b, input c_in, output [N:0] sum);
  reg [N-1:0] p,g,p1,g1,p2,g2,s;
  reg [N-1:0] carry;
  integer i;
   always @(*)
   begin
   
   
   for(i=0;i<N;i=i+1)
   	begin
   	  p[i] <= a[i] ^ b[i];
   	  g[i] <= a[i] & b[i];
   	end  
   
   for(i=0;i<N;i=i+1)
   	if (i == 0) 
   		begin
      		  p1[i] <= p[i];
    		  g1[i] <= g[i]; 
   		end
   	else 
   		begin
     		  p1[i] <= p[i] & p[i-1];
     		  g1[i] <= g[i] || (p[i] & g[i-1]);
   		end
   
   for(i=0;i<N;i=i+1)
   	if (i == 0 )
   		begin
     		  p2[i] <= p1[i];
     		  g2[i] <= g1[i]; 
   		end
   	else 
   	if (i == 1 )
   		begin
     		  p2[i] <= p1[i];
     		  g2[i] <= g1[i]; 
   		end
   	else
   		begin 
   		  p2[i] <= p1[i] & p1[i-2];
   		  g2[i] <= g1[i] || (p1[i] & g1[i-2]);
   		end
   
   for(i=0;i<N;i=i+1)
   	if (i == 0) 
   		begin
   		  s[i] <= p[i] ^ c_in;
   		  carry[i] <= g2[i];
   		end
   	else
   		begin
   		  s[i] <= p[i] ^ carry[i-1];
   		  carry[i] <= g2[i];
   		end
   end
   assign sum = {carry[N-1], s};
endmodule

ksa/ksa_tb.v
`timescale 1ns / 1ns
module ksa_tb;
  reg [3:0]a, b;
  reg c_in;
  wire [4:0]sum;
  ksa ksa1(.a(a), .b(b), .c_in(c_in), .sum(sum));
           
    initial
        begin
            $dumpfile ("ksa_tb.vcd");
            $dumpvars (0, ksa_tb);
            #0 a = 4'b0000;
            #0 b = 4'b0000;
            #0 c_in = 1'b0;
            #100 $finish ;
        end
        always #2 a = a + 2'b11;
	always #2 b = b + 3'b100;
endmodule

ksa/ksa_tb.vcd
$date
	Sun Oct  3 20:35:07 2021
$end
$version
	Icarus Verilog
$end
$timescale
	1ns
$end
$scope module ksa_tb $end
$var wire 5 ! sum [4:0] $end
$var reg 4 " a [3:0] $end
$var reg 4 # b [3:0] $end
$var reg 1 $ c_in $end
$scope module ksa1 $end
$var wire 4 % a [3:0] $end
$var wire 4 & b [3:0] $end
$var wire 1 $ c_in $end
$var wire 5 ' sum [4:0] $end
$var reg 4 ( carry [3:0] $end
$var reg 4 ) g [3:0] $end
$var reg 4 * g1 [3:0] $end
$var reg 4 + g2 [3:0] $end
$var reg 4 , p [3:0] $end
$var reg 4 - p1 [3:0] $end
$var reg 4 . p2 [3:0] $end
$var reg 4 / s [3:0] $end
$var integer 32 0 i [31:0] $end
$upscope $end
$upscope $end
$enddefinitions $end
#0
$dumpvars
b100 0
b0 /
b0 .
b0 -
b0 ,
b0 +
b0 *
b0 )
b0 (
b0 '
b0 &
b0 %
0$
b0 #
b0 "
b0 !
$end
#2
b111 .
b111 !
b111 '
b111 /
b111 -
b111 ,
b100 0
b100 #
b100 &
b11 "
b11 %
#4
b0 .
b1110 !
b1110 '
b1110 /
b1100 -
b1110 ,
b100 0
b1000 #
b1000 &
b110 "
b110 %
#6
b1000 (
b1000 +
b1 .
b10101 !
b10101 '
b101 /
b1000 *
b1 -
b1000 )
b101 ,
b100 0
b1100 #
b1100 &
b1001 "
b1001 %
#8
b0 (
b0 +
b0 .
b1100 !
b1100 '
b1100 /
b0 *
b1000 -
b0 )
b1100 ,
b100 0
b0 #
b0 &
b1100 "
b1100 %
#10
b1100 (
b1100 +
b11 .
b10011 !
b10011 '
b11 /
b1100 *
b11 -
b100 )
b1011 ,
b100 0
b100 #
b100 &
b1111 "
b1111 %
#12
b0 (
b0 +
b0 .
b1010 !
b1010 '
b1010 /
b0 *
b0 -
b0 )
b1010 ,
b100 0
b1000 #
b1000 &
b10 "
b10 %
#14
b1100 (
b1100 +
b1 .
b10001 !
b10001 '
b1 /
b1100 *
b1 -
b100 )
b1001 ,
b100 0
b1100 #
b1100 &
b101 "
b101 %
#16
b0 (
b0 +
b0 .
b1000 !
b1000 '
b1000 /
b0 *
b0 -
b0 )
b1000 ,
b100 0
b0 #
b0 &
b1000 "
b1000 %
#18
b1111 .
b1111 !
b1111 '
b1111 /
b1111 -
b1111 ,
b100 0
b100 #
b100 &
b1011 "
b1011 %
#20
b1000 (
b1000 +
b0 .
b10110 !
b10110 '
b110 /
b1000 *
b100 -
b1000 )
b110 ,
b100 0
b1000 #
b1000 &
b1110 "
b1110 %
#22
b0 (
b0 +
b1 .
b1101 !
b1101 '
b1101 /
b0 *
b1001 -
b0 )
b1101 ,
b100 0
b1100 #
b1100 &
b1 "
b1 %
#24
b0 .
b100 !
b100 '
b100 /
b0 -
b100 ,
b100 0
b0 #
b0 &
b100 "
b100 %
#26
b100 (
b100 +
b11 .
b1011 !
b1011 '
b1011 /
b100 *
b11 -
b100 )
b11 ,
b100 0
b100 #
b100 &
b111 "
b111 %
#28
b1000 (
b1000 +
b0 .
b10010 !
b10010 '
b10 /
b1000 *
b0 -
b1000 )
b10 ,
b100 0
b1000 #
b1000 &
b1010 "
b1010 %
#30
b1100 (
b1100 +
b1 .
b11001 !
b11001 '
b1001 /
b1100 *
b1 -
b1100 )
b1 ,
b100 0
b1100 #
b1100 &
b1101 "
b1101 %
#32
b0 (
b0 +
b0 .
b0 !
b0 '
b0 /
b0 *
b0 -
b0 )
b0 ,
b100 0
b0 #
b0 &
b0 "
b0 %
#34
b111 .
b111 !
b111 '
b111 /
b111 -
b111 ,
b100 0
b100 #
b100 &
b11 "
b11 %
#36
b0 .
b1110 !
b1110 '
b1110 /
b1100 -
b1110 ,
b100 0
b1000 #
b1000 &
b110 "
b110 %
#38
b1000 (
b1000 +
b1 .
b10101 !
b10101 '
b101 /
b1000 *
b1 -
b1000 )
b101 ,
b100 0
b1100 #
b1100 &
b1001 "
b1001 %
#40
b0 (
b0 +
b0 .
b1100 !
b1100 '
b1100 /
b0 *
b1000 -
b0 )
b1100 ,
b100 0
b0 #
b0 &
b1100 "
b1100 %
#42
b1100 (
b1100 +
b11 .
b10011 !
b10011 '
b11 /
b1100 *
b11 -
b100 )
b1011 ,
b100 0
b100 #
b100 &
b1111 "
b1111 %
#44
b0 (
b0 +
b0 .
b1010 !
b1010 '
b1010 /
b0 *
b0 -
b0 )
b1010 ,
b100 0
b1000 #
b1000 &
b10 "
b10 %
#46
b1100 (
b1100 +
b1 .
b10001 !
b10001 '
b1 /
b1100 *
b1 -
b100 )
b1001 ,
b100 0
b1100 #
b1100 &
b101 "
b101 %
#48
b0 (
b0 +
b0 .
b1000 !
b1000 '
b1000 /
b0 *
b0 -
b0 )
b1000 ,
b100 0
b0 #
b0 &
b1000 "
b1000 %
#50
b1111 .
b1111 !
b1111 '
b1111 /
b1111 -
b1111 ,
b100 0
b100 #
b100 &
b1011 "
b1011 %
#52
b1000 (
b1000 +
b0 .
b10110 !
b10110 '
b110 /
b1000 *
b100 -
b1000 )
b110 ,
b100 0
b1000 #
b1000 &
b1110 "
b1110 %
#54
b0 (
b0 +
b1 .
b1101 !
b1101 '
b1101 /
b0 *
b1001 -
b0 )
b1101 ,
b100 0
b1100 #
b1100 &
b1 "
b1 %
#56
b0 .
b100 !
b100 '
b100 /
b0 -
b100 ,
b100 0
b0 #
b0 &
b100 "
b100 %
#58
b100 (
b100 +
b11 .
b1011 !
b1011 '
b1011 /
b100 *
b11 -
b100 )
b11 ,
b100 0
b100 #
b100 &
b111 "
b111 %
#60
b1000 (
b1000 +
b0 .
b10010 !
b10010 '
b10 /
b1000 *
b0 -
b1000 )
b10 ,
b100 0
b1000 #
b1000 &
b1010 "
b1010 %
#62
b1100 (
b1100 +
b1 .
b11001 !
b11001 '
b1001 /
b1100 *
b1 -
b1100 )
b1 ,
b100 0
b1100 #
b1100 &
b1101 "
b1101 %
#64
b0 (
b0 +
b0 .
b0 !
b0 '
b0 /
b0 *
b0 -
b0 )
b0 ,
b100 0
b0 #
b0 &
b0 "
b0 %
#66
b111 .
b111 !
b111 '
b111 /
b111 -
b111 ,
b100 0
b100 #
b100 &
b11 "
b11 %
#68
b0 .
b1110 !
b1110 '
b1110 /
b1100 -
b1110 ,
b100 0
b1000 #
b1000 &
b110 "
b110 %
#70
b1000 (
b1000 +
b1 .
b10101 !
b10101 '
b101 /
b1000 *
b1 -
b1000 )
b101 ,
b100 0
b1100 #
b1100 &
b1001 "
b1001 %
#72
b0 (
b0 +
b0 .
b1100 !
b1100 '
b1100 /
b0 *
b1000 -
b0 )
b1100 ,
b100 0
b0 #
b0 &
b1100 "
b1100 %
#74
b1100 (
b1100 +
b11 .
b10011 !
b10011 '
b11 /
b1100 *
b11 -
b100 )
b1011 ,
b100 0
b100 #
b100 &
b1111 "
b1111 %
#76
b0 (
b0 +
b0 .
b1010 !
b1010 '
b1010 /
b0 *
b0 -
b0 )
b1010 ,
b100 0
b1000 #
b1000 &
b10 "
b10 %
#78
b1100 (
b1100 +
b1 .
b10001 !
b10001 '
b1 /
b1100 *
b1 -
b100 )
b1001 ,
b100 0
b1100 #
b1100 &
b101 "
b101 %
#80
b0 (
b0 +
b0 .
b1000 !
b1000 '
b1000 /
b0 *
b0 -
b0 )
b1000 ,
b100 0
b0 #
b0 &
b1000 "
b1000 %
#82
b1111 .
b1111 !
b1111 '
b1111 /
b1111 -
b1111 ,
b100 0
b100 #
b100 &
b1011 "
b1011 %
#84
b1000 (
b1000 +
b0 .
b10110 !
b10110 '
b110 /
b1000 *
b100 -
b1000 )
b110 ,
b100 0
b1000 #
b1000 &
b1110 "
b1110 %
#86
b0 (
b0 +
b1 .
b1101 !
b1101 '
b1101 /
b0 *
b1001 -
b0 )
b1101 ,
b100 0
b1100 #
b1100 &
b1 "
b1 %
#88
b0 .
b100 !
b100 '
b100 /
b0 -
b100 ,
b100 0
b0 #
b0 &
b100 "
b100 %
#90
b100 (
b100 +
b11 .
b1011 !
b1011 '
b1011 /
b100 *
b11 -
b100 )
b11 ,
b100 0
b100 #
b100 &
b111 "
b111 %
#92
b1000 (
b1000 +
b0 .
b10010 !
b10010 '
b10 /
b1000 *
b0 -
b1000 )
b10 ,
b100 0
b1000 #
b1000 &
b1010 "
b1010 %
#94
b1100 (
b1100 +
b1 .
b11001 !
b11001 '
b1001 /
b1100 *
b1 -
b1100 )
b1 ,
b100 0
b1100 #
b1100 &
b1101 "
b1101 %
#96
b0 (
b0 +
b0 .
b0 !
b0 '
b0 /
b0 *
b0 -
b0 )
b0 ,
b100 0
b0 #
b0 &
b0 "
b0 %
#98
b111 .
b111 !
b111 '
b111 /
b111 -
b111 ,
b100 0
b100 #
b100 &
b11 "
b11 %
#100
b0 .
b1110 !
b1110 '
b1110 /
b1100 -
b1110 ,
b100 0
b1000 #
b1000 &
b110 "
b110 %
