masked_rca/m_rca.v
//This is the definition of a masked n-bit ripple carry full_adder
module f_a(a0, a1, b0, b1, c_in, s, c_out);
      input a0, a1, b0, b1, c_in;
      output s, c_out;
      reg s, c_out, a,b,d, e, f;
      always @(*)
      begin
        a <= a0 ^ a1;
      	b <= b0 ^ b1;
      	d <= a & b;
      	e <= b & c_in;
      	f <= c_in & a;
      	s <= a ^ b ^ c_in;
      	c_out <= d | e | f;
      end
endmodule


module m_rca #(parameter N=4)(input [N-1:0] a0,a1,b0,b1, output [N:0] sum);
  wire [N:0] carry;
  wire [N-1 : 0]s;
  assign carry[0] = 1'b0;
   
   genvar i;
   generate 
   for(i=0;i<N;i=i+1)
     begin     	
     	f_a f(a0[i], a1[i], b0[i], b1[i], carry[i], s[i], carry[i+1]);
     end
     endgenerate
   assign sum = {carry[N], s};
endmodule

masked_rca/m_rca_tb.v
`timescale 1ns / 1ns
module m_rca_tb;
  reg [3:0]a0, a1, b0, b1;
  wire [4:0]sum;
  m_rca mrca(.a0(a0), .a1(a1), .b0(b0), .b1(b1), .sum(sum));
           
    initial
        begin
            $dumpfile ("m_rca_tb.vcd");
            $dumpvars (0, m_rca_tb);
            #0 a0 = 4'b0000;
            #0 a1 = 4'b0001;
            #0 b0 = 4'b0010;
            #0 b1 = 4'b0100;
            #20 $finish ;
        end
        always #2 a0 = a0 + 1'b1;
	always #2 a1 = a1 + 1'b1;
	always #2 b0 = b0 + 1'b1;
	always #2 b1 = b1 + 1'b1;
endmodule

masked_rca/m_rca_tb.vcd
$date
	Sun Oct  3 20:36:49 2021
$end
$version
	Icarus Verilog
$end
$timescale
	1ns
$end
$scope module m_rca_tb $end
$var wire 5 ! sum [4:0] $end
$var reg 4 " a0 [3:0] $end
$var reg 4 # a1 [3:0] $end
$var reg 4 $ b0 [3:0] $end
$var reg 4 % b1 [3:0] $end
$scope module mrca $end
$var wire 4 & a0 [3:0] $end
$var wire 4 ' a1 [3:0] $end
$var wire 4 ( b0 [3:0] $end
$var wire 4 ) b1 [3:0] $end
$var wire 5 * sum [4:0] $end
$var wire 4 + s [3:0] $end
$var wire 5 , carry [4:0] $end
$scope begin genblk1[0] $end
$scope module f $end
$var wire 1 - a0 $end
$var wire 1 . a1 $end
$var wire 1 / b0 $end
$var wire 1 0 b1 $end
$var wire 1 1 c_in $end
$var reg 1 2 a $end
$var reg 1 3 b $end
$var reg 1 4 c_out $end
$var reg 1 5 d $end
$var reg 1 6 e $end
$var reg 1 7 f $end
$var reg 1 8 s $end
$upscope $end
$upscope $end
$scope begin genblk1[1] $end
$scope module f $end
$var wire 1 9 a0 $end
$var wire 1 : a1 $end
$var wire 1 ; b0 $end
$var wire 1 < b1 $end
$var wire 1 = c_in $end
$var reg 1 > a $end
$var reg 1 ? b $end
$var reg 1 @ c_out $end
$var reg 1 A d $end
$var reg 1 B e $end
$var reg 1 C f $end
$var reg 1 D s $end
$upscope $end
$upscope $end
$scope begin genblk1[2] $end
$scope module f $end
$var wire 1 E a0 $end
$var wire 1 F a1 $end
$var wire 1 G b0 $end
$var wire 1 H b1 $end
$var wire 1 I c_in $end
$var reg 1 J a $end
$var reg 1 K b $end
$var reg 1 L c_out $end
$var reg 1 M d $end
$var reg 1 N e $end
$var reg 1 O f $end
$var reg 1 P s $end
$upscope $end
$upscope $end
$scope begin genblk1[3] $end
$scope module f $end
$var wire 1 Q a0 $end
$var wire 1 R a1 $end
$var wire 1 S b0 $end
$var wire 1 T b1 $end
$var wire 1 U c_in $end
$var reg 1 V a $end
$var reg 1 W b $end
$var reg 1 X c_out $end
$var reg 1 Y d $end
$var reg 1 Z e $end
$var reg 1 [ f $end
$var reg 1 \ s $end
$upscope $end
$upscope $end
$upscope $end
$upscope $end
$enddefinitions $end
#0
$dumpvars
0\
0[
0Z
0Y
0X
0W
0V
0U
0T
0S
0R
0Q
1P
0O
0N
0M
0L
1K
0J
0I
1H
0G
0F
0E
1D
0C
0B
0A
0@
1?
0>
0=
0<
1;
0:
09
18
07
06
05
04
03
12
01
00
0/
1.
0-
b0 ,
b111 +
b111 *
b100 )
b10 (
b1 '
b0 &
b100 %
b10 $
b1 #
b0 "
b111 !
$end
#2
1\
1U
1L
0P
1N
1I
b1100 ,
1@
b1001 !
b1001 *
b1001 +
0D
1A
1>
10
1/
0.
1:
1-
b101 %
b101 )
b11 $
b11 (
b10 #
b10 '
b1 "
b1 &
#4
0\
0U
0I
0L
b0 ,
0@
0P
0N
b11 !
b11 *
b11 +
1D
0A
0K
0>
00
1<
0/
0;
1G
1.
0-
19
b110 %
b110 )
b100 $
b100 (
b11 #
b11 '
b10 "
b10 &
#6
1\
1U
1L
1O
1I
b1100 ,
1@
0D
1A
b1001 !
b1001 *
b1001 +
0P
1>
1J
10
1/
0.
0:
1F
1-
b111 %
b111 )
b101 $
b101 (
b100 #
b100 '
b11 "
b11 &
#8
0U
0L
1P
0I
0X
b0 ,
0@
1\
0Z
b1111 !
b1111 *
b1111 +
1D
0A
0O
0N
1W
0>
1K
0J
00
0<
0H
1T
0/
1;
1.
0-
09
1E
b1000 %
b1000 )
b110 $
b110 (
b101 #
b101 '
b100 "
b100 &
#10
1X
0\
1Z
1U
1L
0P
1N
1I
b11100 ,
1@
b10001 !
b10001 *
b1 +
0D
1A
1>
10
1/
0.
1:
1-
b1001 %
b1001 )
b111 $
b111 (
b110 #
b110 '
b101 "
b101 &
#12
0U
0I
0L
0X
b0 ,
0@
0P
0N
0\
0Z
b11 !
b11 *
b11 +
1D
0A
0K
0W
0>
00
1<
0/
0;
0G
1S
1.
0-
19
b1010 %
b1010 )
b1000 $
b1000 (
b111 #
b111 '
b110 "
b110 &
#14
1X
1[
1U
1L
1O
1I
b11100 ,
1@
0D
1A
0P
b10001 !
b10001 *
b1 +
0\
1>
1J
1V
10
1/
0.
0:
0F
1R
1-
b1011 %
b1011 )
b1001 $
b1001 (
b1000 #
b1000 '
b111 "
b111 &
#16
0U
0L
1P
0I
0@
b0 ,
0X
1D
0A
0O
0N
b111 !
b111 *
b111 +
0\
0[
0>
1K
0J
0V
00
0<
1H
0/
1;
1.
0-
09
0E
1Q
b1100 %
b1100 )
b1010 $
b1010 (
b1001 #
b1001 '
b1000 "
b1000 &
#18
1\
1U
1L
0P
1N
1I
b1100 ,
1@
b1001 !
b1001 *
b1001 +
0D
1A
1>
10
1/
0.
1:
1-
b1101 %
b1101 )
b1011 $
b1011 (
b1010 #
b1010 '
b1001 "
b1001 &
#20
0\
0U
0I
0L
b0 ,
0@
0P
0N
b11 !
b11 *
b11 +
1D
0A
0K
0>
00
1<
0/
0;
1G
1.
0-
19
b1110 %
b1110 )
b1100 $
b1100 (
b1011 #
b1011 '
b1010 "
b1010 &
