pipelined_masked_rca/pipe_rca.v
//This is the definition of a masked n-bit ripple carry full_adder
module pipe_rca #(parameter N= 4)(input [N-1:0] a0,a1,b0,b1, input clk1, clk2, clk3, clk4,clk5, output [N:0] sum);

    reg c_in;
    reg [3:0]s, s0, s1, c_out, a,b,d, e, f;  
    reg sum;
  always @ (posedge clk1)
    begin
    	c_in <= 1'b0;  
    	a[0] <= a0[0] ^ a1[0];
      	b[0] <= b0[0] ^ b1[0];
      	d[0] <= a[0] & b[0];
      	e[0] <= b[0] & c_in;
      	f[0] <= c_in & a[0];
      	s0[0] <= a0[0] ^ b0[0] ^ c_in;
      	s1[0] <= a1[0] ^ b1[0] ^ c_in;
      	s[0] <= s0[0] ^ s1[0];
      	c_out[0] <= d[0] | e[0] | f[0];
    end
  
  always @(posedge clk2)
  begin
    	a[1] <= a0[1] ^ a1[1];
      	b[1] <= b0[1] ^ b1[1];
      	d[1] <= a[1] & b[1];
      	e[1] <= b[1] & c_out[0];
      	f[1] <= c_out[0] & a[1];
      	s0[1] <= a0[1] ^ b0[1] ^ c_out[0];
      	s1[1] <= a1[1] ^ b1[1] ^ c_out[0];
      	s[1] <= s0[1] ^ s1[1];
      	c_out[1] <= d[1] | e[1] | f[1];
  end
  
 always @(posedge clk3)
  begin
    	a[2] <= a0[2] ^ a1[2];
      	b[2] <= b0[2] ^ b1[2];
      	d[2] <= a[2] & b[2];
      	e[2] <= b[2] & c_out[1];
      	f[2] <= c_out[1] & a[2];
      	s0[2] <= a0[2] ^ b0[2] ^ c_out[1];
      	s1[2] <= a1[2] ^ b1[2] ^ c_out[1];
      	s[2] <= s0[2] ^ s1[2];
      	c_out[2] <= d[2] | e[2] | f[2];
  end
  
  always @(posedge clk4)
  begin
    	a[3] <= a0[3] ^ a1[3];
      	b[3] <= b0[3] ^ b1[3];
      	d[3] <= a[3] & b[3];
      	e[3] <= b[3] & c_out[2];
      	f[3] <= c_out[2] & a[3];
      	s0[3] <= a0[3] ^ b0[3] ^ c_out[2];
      	s1[3] <= a1[3] ^ b1[3] ^ c_out[2];
      	s[3] <= s0[3] ^ s1[3];
      	c_out[3] <= d[3] | e[3] | f[3];
  end
  always @(posedge clk5)
  begin
  	sum <= {c_out[3], s};
  end
endmodule

pipelined_masked_rca/pipe_rca_tb.v
`timescale 1ns / 1ns
module pipe_rca_tb;
  reg [3:0]a0, a1, b0, b1;
  reg clk1, clk2, clk3, clk4, clk5;
  wire [4:0]sum;
  integer i = 0;
  pipe_rca pipe_rca1(.a0(a0), .a1(a1), .b0(b0), .b1(b1), .sum(sum), .clk1(clk1), .clk2(clk2), .clk3(clk3), .clk4(clk4), .clk5(clk5));
        
   initial begin
		$dumpfile ("pipe_rca_tb.vcd");
        	$dumpvars (0, pipe_rca_tb);	
    	    	a0 = 4'b0000;
            	a1 = 4'b0001;
            	b0 = 4'b0010;
            	b1 = 4'b0100;
		clk1 = 1'b0;
    	    	forever #2 clk1 = ~clk1;
    end
    initial begin
    		clk2 = 1'b0;
    		forever #4 clk2 = ~clk2;
    end
    initial begin
    		clk3 = 1'b0;
    		forever #8 clk3 = ~clk3;
    end
    initial begin
    		clk4 = 1'b0;
    		forever #16 clk4 = ~clk4;
    end
    initial begin
    		clk5 = 1'b0;
    		forever #32 clk5 = ~clk5;
    end

      	initial begin
	while (i < 4) begin 
    	a0 <= a0 + 1'b1; @(posedge clk5);
    	a1 <= a1 + 1'b1; @(posedge clk5);
    	b0 <= b0 + 1'b1; @(posedge clk5);
    	b1 <= b1 + 1'b1; @(posedge clk5);
    	i += 1;
    	end
    	#1200 $finish ;
    	end

endmodule

pipelined_masked_rca/pipe_rca_tb.vcd
$date
	Wed Sep 29 03:44:40 2021
$end
$version
	Icarus Verilog
$end
$timescale
	1ns
$end
$scope module pipe_rca_tb $end
$var wire 5 ! sum [4:0] $end
$var reg 4 " a0 [3:0] $end
$var reg 4 # a1 [3:0] $end
$var reg 4 $ b0 [3:0] $end
$var reg 4 % b1 [3:0] $end
$var reg 1 & clk1 $end
$var reg 1 ' clk2 $end
$var reg 1 ( clk3 $end
$var reg 1 ) clk4 $end
$var reg 1 * clk5 $end
$var integer 32 + i [31:0] $end
$scope module pipe_rca1 $end
$var wire 4 , a0 [3:0] $end
$var wire 4 - a1 [3:0] $end
$var wire 4 . b0 [3:0] $end
$var wire 4 / b1 [3:0] $end
$var wire 1 & clk1 $end
$var wire 1 ' clk2 $end
$var wire 1 ( clk3 $end
$var wire 1 ) clk4 $end
$var wire 1 * clk5 $end
$var reg 4 0 a [3:0] $end
$var reg 4 1 b [3:0] $end
$var reg 1 2 c_in $end
$var reg 4 3 c_out [3:0] $end
$var reg 4 4 d [3:0] $end
$var reg 4 5 e [3:0] $end
$var reg 4 6 f [3:0] $end
$var reg 4 7 s [3:0] $end
$var reg 4 8 s0 [3:0] $end
$var reg 4 9 s1 [3:0] $end
$var reg 5 : sum [4:0] $end
$upscope $end
$upscope $end
$enddefinitions $end
#0
$dumpvars
bx :
bx 9
bx 8
bx 7
bx 6
bx 5
bx 4
bx 3
x2
bx 1
bx 0
b100 /
b10 .
b1 -
b1 ,
b0 +
0*
0)
0(
0'
0&
b100 %
b10 $
b1 #
b1 "
bx !
$end
#2
bx0 1
bx0 0
02
1&
#4
bx10 1
bx00 0
0&
1'
#6
bx1 9
bx1 8
bx0 6
bx0 5
bx0 4
1&
#8
bx110 1
bx000 0
0&
0'
1(
#10
bx0 3
bx0 7
1&
#12
bx01 9
bx11 8
bx00 6
bx00 5
bx00 4
0&
1'
#14
1&
#16
b110 1
b0 0
0&
0'
0(
1)
#18
1&
#20
bx00 3
bx10 7
0&
1'
#22
1&
#24
bx101 9
bx011 8
bx000 6
bx000 5
bx000 4
0&
0'
1(
#26
1&
#28
0&
1'
#30
1&
#32
bx10 !
bx10 :
b10 #
b10 -
0&
0'
0(
0)
1*
#34
bx100 9
b1 0
1&
#36
bx110 9
b11 0
0&
1'
#38
bx11 7
1&
#40
bx000 3
bx111 7
0&
0'
1(
#42
1&
#44
bx101 7
bx010 4
0&
1'
#46
1&
#48
b110 9
b11 8
b0 6
b0 5
b10 4
0&
0'
0(
1)
#50
1&
#52
bx010 3
0&
1'
#54
1&
#56
b10 9
b111 8
b100 5
0&
0'
1(
#58
1&
#60
0&
1'
#62
1&
#64
0&
0'
0(
0)
0*
#66
1&
#68
0&
1'
#70
1&
#72
bx110 3
0&
0'
1(
#74
1&
#76
0&
1'
#78
1&
#80
b110 3
b101 7
b1010 9
b1111 8
0&
0'
0(
1)
#82
1&
#84
0&
1'
#86
1&
#88
0&
0'
1(
#90
1&
#92
0&
1'
#94
1&
#96
b11 $
b11 .
b101 !
b101 :
0&
0'
0(
0)
1*
#98
b1110 8
b111 1
1&
#100
0&
1'
#102
b100 7
b11 4
1&
#104
0&
0'
1(
#106
b111 3
1&
#108
b1000 9
b1100 8
b10 6
b110 5
0&
1'
#110
1&
#112
0&
0'
0(
1)
#114
1&
#116
0&
1'
#118
1&
#120
0&
0'
1(
#122
1&
#124
0&
1'
#126
1&
#128
0&
0'
0(
0)
0*
#130
1&
#132
0&
1'
#134
1&
#136
0&
0'
1(
#138
1&
#140
0&
1'
#142
1&
#144
0&
0'
0(
1)
#146
1&
#148
0&
1'
#150
1&
#152
0&
0'
1(
#154
1&
#156
0&
1'
#158
1&
#160
b100 !
b100 :
b101 %
b101 /
0&
0'
0(
0)
1*
#162
b1001 9
b110 1
1&
#164
0&
1'
#166
b101 7
b10 4
1&
#168
0&
0'
1(
#170
b110 3
1&
#172
b1011 9
b1110 8
b0 6
b100 5
0&
1'
#174
1&
#176
0&
0'
0(
1)
#178
1&
#180
0&
1'
#182
1&
#184
0&
0'
1(
#186
1&
#188
0&
1'
#190
1&
#192
0&
0'
0(
0)
0*
#194
1&
#196
0&
1'
#198
1&
#200
0&
0'
1(
#202
1&
#204
0&
1'
#206
1&
#208
0&
0'
0(
1)
#210
1&
#212
0&
1'
#214
1&
#216
0&
0'
1(
#218
1&
#220
0&
1'
#222
1&
#224
b10 "
b10 ,
b101 !
b101 :
b1 +
0&
0'
0(
0)
1*
#226
b1111 8
b10 0
1&
#228
b1101 8
b0 0
0&
1'
#230
b100 7
1&
#232
0&
0'
1(
#234
1&
#236
b110 7
b0 4
0&
1'
#238
1&
#240
0&
0'
0(
1)
#242
1&
#244
b100 3
0&
1'
#246
1&
#248
b1111 9
b1001 8
b0 5
0&
0'
1(
#250
1&
#252
0&
1'
#254
1&
#256
0&
0'
0(
0)
0*
#258
1&
#260
0&
1'
#262
1&
#264
b0 3
0&
0'
1(
#266
1&
#268
0&
1'
#270
1&
#272
b111 9
b1 8
0&
0'
0(
1)
#274
1&
#276
0&
1'
#278
1&
#280
0&
0'
1(
#282
1&
#284
0&
1'
#286
1&
#288
b110 !
b110 :
b11 #
b11 -
0&
0'
0(
0)
1*
#290
b110 9
b1 0
1&
#292
0&
1'
#294
b111 7
1&
#296
0&
0'
1(
#298
1&
#300
0&
1'
#302
1&
#304
0&
0'
0(
1)
#306
1&
#308
0&
1'
#310
1&
#312
0&
0'
1(
#314
1&
#316
0&
1'
#318
1&
#320
0&
0'
0(
0)
0*
#322
1&
#324
0&
1'
#326
1&
#328
0&
0'
1(
#330
1&
#332
0&
1'
#334
1&
#336
0&
0'
0(
1)
#338
1&
#340
0&
1'
#342
1&
#344
0&
0'
1(
#346
1&
#348
0&
1'
#350
1&
#352
b100 $
b100 .
b111 !
b111 :
0&
0'
0(
0)
1*
#354
b0 8
b111 1
1&
#356
b10 8
b101 1
0&
1'
#358
b110 7
b1 4
1&
#360
b110 8
b1 1
0&
0'
1(
#362
b1 3
1&
#364
b100 7
b100 9
b100 8
0&
1'
#366
1&
#368
0&
0'
0(
1)
#370
1&
#372
0&
1'
#374
1&
#376
b0 7
0&
0'
1(
#378
1&
#380
0&
1'
#382
1&
#384
0&
0'
0(
0)
0*
#386
1&
#388
0&
1'
#390
1&
#392
0&
0'
1(
#394
1&
#396
0&
1'
#398
1&
#400
0&
0'
0(
1)
#402
1&
#404
0&
1'
#406
1&
#408
0&
0'
1(
#410
1&
#412
0&
1'
#414
1&
#416
b0 !
b0 :
b110 %
b110 /
0&
0'
0(
0)
1*
#418
b101 9
b0 1
1&
#420
b111 9
b10 1
0&
1'
#422
b1 7
b0 4
1&
#424
0&
0'
1(
#426
b0 3
1&
#428
b11 7
b101 9
b110 8
0&
1'
#430
1&
#432
0&
0'
0(
1)
#434
1&
#436
0&
1'
#438
1&
#440
0&
0'
1(
#442
1&
#444
0&
1'
#446
1&
#448
0&
0'
0(
0)
0*
#450
1&
#452
0&
1'
#454
1&
#456
0&
0'
1(
#458
1&
#460
0&
1'
#462
1&
#464
0&
0'
0(
1)
#466
1&
#468
0&
1'
#470
1&
#472
0&
0'
1(
#474
1&
#476
0&
1'
#478
1&
#480
b11 "
b11 ,
b11 !
b11 :
b10 +
0&
0'
0(
0)
1*
#482
b111 8
b0 0
1&
#484
0&
1'
#486
b10 7
1&
#488
0&
0'
1(
#490
1&
#492
0&
1'
#494
1&
#496
0&
0'
0(
1)
#498
1&
#500
0&
1'
#502
1&
#504
0&
0'
1(
#506
1&
#508
0&
1'
#510
1&
#512
0&
0'
0(
0)
0*
#514
1&
#516
0&
1'
#518
1&
#520
0&
0'
1(
#522
1&
#524
0&
1'
#526
1&
#528
0&
0'
0(
1)
#530
1&
#532
0&
1'
#534
1&
#536
0&
0'
1(
#538
1&
#540
0&
1'
#542
1&
#544
b10 !
b10 :
b100 #
b100 -
0&
0'
0(
0)
1*
#546
b100 9
b1 0
1&
#548
b110 9
b11 0
0&
1'
#550
b11 7
1&
#552
b10 9
b111 0
0&
0'
1(
#554
1&
#556
b1 7
b10 4
0&
1'
#558
1&
#560
0&
0'
0(
1)
#562
1&
#564
b10 3
0&
1'
#566
1&
#568
b101 7
b110 9
b11 8
b100 6
0&
0'
1(
#570
1&
#572
0&
1'
#574
1&
#576
0&
0'
0(
0)
0*
#578
1&
#580
0&
1'
#582
1&
#584
b110 3
0&
0'
1(
#586
1&
#588
0&
1'
#590
1&
#592
b1110 9
b1011 8
0&
0'
0(
1)
#594
1&
#596
0&
1'
#598
1&
#600
0&
0'
1(
#602
1&
#604
0&
1'
#606
1&
#608
b101 $
b101 .
b101 !
b101 :
0&
0'
0(
0)
1*
#610
b1010 8
b11 1
1&
#612
0&
1'
#614
b100 7
b11 4
1&
#616
0&
0'
1(
#618
b111 3
1&
#620
b1100 9
b1000 8
b110 6
b10 5
0&
1'
#622
1&
#624
0&
0'
0(
1)
#626
1&
#628
0&
1'
#630
1&
#632
0&
0'
1(
#634
1&
#636
0&
1'
#638
1&
#640
0&
0'
0(
0)
0*
#642
1&
#644
0&
1'
#646
1&
#648
0&
0'
1(
#650
1&
#652
0&
1'
#654
1&
#656
0&
0'
0(
1)
#658
1&
#660
0&
1'
#662
1&
#664
0&
0'
1(
#666
1&
#668
0&
1'
#670
1&
#672
b100 !
b100 :
b111 %
b111 /
0&
0'
0(
0)
1*
#674
b1101 9
b10 1
1&
#676
0&
1'
#678
b101 7
b10 4
1&
#680
0&
0'
1(
#682
b110 3
1&
#684
b1111 9
b1010 8
b100 6
b0 5
0&
1'
#686
1&
#688
0&
0'
0(
1)
#690
1&
#692
0&
1'
#694
1&
#696
0&
0'
1(
#698
1&
#700
0&
1'
#702
1&
#704
0&
0'
0(
0)
0*
#706
1&
#708
0&
1'
#710
1&
#712
0&
0'
1(
#714
1&
#716
0&
1'
#718
1&
#720
0&
0'
0(
1)
#722
1&
#724
0&
1'
#726
1&
#728
0&
0'
1(
#730
1&
#732
0&
1'
#734
1&
#736
b100 "
b100 ,
b101 !
b101 :
b11 +
0&
0'
0(
0)
1*
#738
b1011 8
b110 0
1&
#740
b1001 8
b100 0
0&
1'
#742
b100 7
1&
#744
b1101 8
b0 0
0&
0'
1(
#746
1&
#748
b110 7
b0 4
0&
1'
#750
1&
#752
0&
0'
0(
1)
#754
1&
#756
b100 3
0&
1'
#758
1&
#760
b10 7
b1011 9
b1001 8
b0 6
0&
0'
1(
#762
1&
#764
0&
1'
#766
1&
#768
0&
0'
0(
0)
0*
#770
1&
#772
0&
1'
#774
1&
#776
b0 3
0&
0'
1(
#778
1&
#780
0&
1'
#782
1&
#784
b11 9
b1 8
0&
0'
0(
1)
#786
1&
#788
0&
1'
#790
1&
#792
0&
0'
1(
#794
1&
#796
0&
1'
#798
1&
#800
b10 !
b10 :
b101 #
b101 -
0&
0'
0(
0)
1*
#802
b10 9
b1 0
1&
#804
0&
1'
#806
b11 7
1&
#808
0&
0'
1(
#810
1&
#812
0&
1'
#814
1&
#816
0&
0'
0(
1)
#818
1&
#820
0&
1'
#822
1&
#824
0&
0'
1(
#826
1&
#828
0&
1'
#830
1&
#832
0&
0'
0(
0)
0*
#834
1&
#836
0&
1'
#838
1&
#840
0&
0'
1(
#842
1&
#844
0&
1'
#846
1&
#848
0&
0'
0(
1)
#850
1&
#852
0&
1'
#854
1&
#856
0&
0'
1(
#858
1&
#860
0&
1'
#862
1&
#864
b110 $
b110 .
b11 !
b11 :
0&
0'
0(
0)
1*
#866
b0 8
b11 1
1&
#868
b10 8
b1 1
0&
1'
#870
b10 7
b1 4
1&
#872
0&
0'
1(
#874
b1 3
1&
#876
b0 7
b0 9
b0 8
0&
1'
#878
1&
#880
0&
0'
0(
1)
#882
1&
#884
0&
1'
#886
1&
#888
0&
0'
1(
#890
1&
#892
0&
1'
#894
1&
#896
0&
0'
0(
0)
0*
#898
1&
#900
0&
1'
#902
1&
#904
0&
0'
1(
#906
1&
#908
0&
1'
#910
1&
#912
0&
0'
0(
1)
#914
1&
#916
0&
1'
#918
1&
#920
0&
0'
1(
#922
1&
#924
0&
1'
#926
1&
#928
b0 !
b0 :
b1000 %
b1000 /
0&
0'
0(
0)
1*
#930
b1 9
b0 1
1&
#932
b11 9
b10 1
0&
1'
#934
b1 7
b0 4
1&
#936
b111 9
b110 1
0&
0'
1(
#938
b0 3
1&
#940
b11 7
b101 9
b10 8
0&
1'
#942
1&
#944
b1101 9
b1110 1
0&
0'
0(
1)
#946
1&
#948
0&
1'
#950
1&
#952
b111 7
0&
0'
1(
#954
1&
#956
0&
1'
#958
1&
#960
0&
0'
0(
0)
0*
#962
1&
#964
0&
1'
#966
1&
#968
0&
0'
1(
#970
1&
#972
0&
1'
#974
1&
#976
b1111 7
0&
0'
0(
1)
#978
1&
#980
0&
1'
#982
1&
#984
0&
0'
1(
#986
1&
#988
0&
1'
#990
1&
#992
b1111 !
b1111 :
b100 +
0&
0'
0(
0)
1*
