rca/rca.v
//This is the definition of a n-bit ripple carry full_adder
module f_a(a,b, c_in, s, c_out);
      input a,b, c_in;
      output s, c_out;
      reg s, c_out, d, e, f;
      always @(*)
      begin
        d <= a & b;
      	e <= b & c_in;
      	f <= c_in & a;
      	s <= a ^ b ^ c_in;
      	c_out <= d | e | f;
      end
endmodule


module rca #(parameter N=4)(input [N-1:0] a,b, input c_in, output [N:0] sum);
  wire [N:0] carry;
  wire [N-1 : 0]s;
  assign carry[0] = c_in;
   
   genvar i;
   generate 
   for(i=0;i<N;i=i+1)
     begin     	
     	f_a f(a[i], b[i], carry[i], s[i], carry[i+1]);
     end
     endgenerate
   assign sum = {carry[N], s};
endmodule

rca/rca_tb.v
`timescale 1ns / 1ns
module rca_tb;
  reg [3:0]a, b;
  reg c_in;
  wire [4:0]sum;
  rca rca1(.a(a), .b(b), .c_in(c_in), .sum(sum));
           
    initial
        begin
            $dumpfile ("rca_tb.vcd");
            $dumpvars (0, rca_tb);
            #0 a = 4'b0000;
            #0 b = 4'b0001;
            #0 c_in = 1'b0;
            #20 $finish ;
        end
        always #2 a = a + 1'b1;
	always #2 b = b + 1'b1;
	always #2 c_in = c_in + 1'b1;
endmodule

rca/rca_tb.vcd
$date
	Tue Sep 28 21:54:18 2021
$end
$version
	Icarus Verilog
$end
$timescale
	1ns
$end
$scope module rca_tb $end
$var wire 5 ! sum [4:0] $end
$var reg 4 " a [3:0] $end
$var reg 4 # b [3:0] $end
$var reg 1 $ c_in $end
$scope module rca1 $end
$var wire 4 % a [3:0] $end
$var wire 4 & b [3:0] $end
$var wire 1 $ c_in $end
$var wire 5 ' sum [4:0] $end
$var wire 4 ( s [3:0] $end
$var wire 5 ) carry [4:0] $end
$scope begin genblk1[0] $end
$scope module f $end
$var wire 1 * a $end
$var wire 1 + b $end
$var wire 1 , c_in $end
$var reg 1 - c_out $end
$var reg 1 . d $end
$var reg 1 / e $end
$var reg 1 0 f $end
$var reg 1 1 s $end
$upscope $end
$upscope $end
$scope begin genblk1[1] $end
$scope module f $end
$var wire 1 2 a $end
$var wire 1 3 b $end
$var wire 1 4 c_in $end
$var reg 1 5 c_out $end
$var reg 1 6 d $end
$var reg 1 7 e $end
$var reg 1 8 f $end
$var reg 1 9 s $end
$upscope $end
$upscope $end
$scope begin genblk1[2] $end
$scope module f $end
$var wire 1 : a $end
$var wire 1 ; b $end
$var wire 1 < c_in $end
$var reg 1 = c_out $end
$var reg 1 > d $end
$var reg 1 ? e $end
$var reg 1 @ f $end
$var reg 1 A s $end
$upscope $end
$upscope $end
$scope begin genblk1[3] $end
$scope module f $end
$var wire 1 B a $end
$var wire 1 C b $end
$var wire 1 D c_in $end
$var reg 1 E c_out $end
$var reg 1 F d $end
$var reg 1 G e $end
$var reg 1 H f $end
$var reg 1 I s $end
$upscope $end
$upscope $end
$upscope $end
$upscope $end
$enddefinitions $end
#0
$dumpvars
0I
0H
0G
0F
0E
0D
0C
0B
0A
0@
0?
0>
0=
0<
0;
0:
09
08
07
06
05
04
03
02
11
00
0/
0.
0-
0,
1+
0*
b0 )
b1 (
b1 '
b1 &
b0 %
0$
b1 #
b0 "
b1 !
$end
#2
1A
1<
15
17
14
1-
09
b100 !
b100 '
b100 (
01
10
1,
0+
13
1*
b111 )
1$
b10 #
b10 &
b1 "
b1 %
#4
07
04
0-
11
00
b101 !
b101 '
b101 (
09
08
16
0,
1+
0*
12
b100 )
0$
b11 #
b11 &
b10 "
b10 %
#6
1I
18
1<
1D
14
15
1=
1-
09
06
0A
1?
b1000 !
b1000 '
b1000 (
01
10
1,
0+
03
1;
1*
b1111 )
1$
b100 #
b100 &
b11 "
b11 %
#8
0?
04
0<
0-
05
11
00
09
08
b1001 !
b1001 '
b1001 (
0A
0@
1>
0,
1+
0*
02
1:
b1000 )
0$
b101 #
b101 &
b100 "
b100 %
#10
1A
1@
1?
1<
15
17
14
1-
09
b1100 !
b1100 '
b1100 (
01
10
1,
0+
13
1*
b1111 )
1$
b110 #
b110 &
b101 "
b101 %
#12
07
04
0-
11
00
b1101 !
b1101 '
b1101 (
09
08
16
0,
1+
0*
12
b1100 )
0$
b111 #
b111 &
b110 "
b110 %
#14
1D
1=
1@
18
1<
14
15
1E
1-
09
06
0A
0?
0>
0I
1G
b10000 !
b10000 '
b0 (
01
10
1,
0+
03
0;
1C
1*
b11111 )
1$
b1000 #
b1000 &
b111 "
b111 %
#16
0G
04
0<
0D
0-
05
0=
11
00
09
08
0A
0@
b10001 !
b10001 '
b1 (
0I
0H
1F
0,
1+
0*
02
0:
1B
b10000 )
0$
b1001 #
b1001 &
b1000 "
b1000 %
#18
1A
1<
15
17
14
1-
09
b10100 !
b10100 '
b100 (
01
10
1,
0+
13
1*
b10111 )
1$
b1010 #
b1010 &
b1001 "
b1001 %
#20
07
04
0-
11
00
b10101 !
b10101 '
b101 (
09
08
16
0,
1+
0*
12
b10100 )
0$
b1011 #
b1011 &
b1010 "
b1010 %
