rca/rca.v
//This is the definition of a 4-bit ripple carry full_adder
module f_a(a,b, c_in, s, c_out);
      input a,b, c_in;
      output s, c_out;
      reg s, c_out, d, e, f;
      always @(*)
      begin
        d <= a & b;
      	e <= b & c_in;
      	f <= c_in & a;
      	s <= a ^ b ^ c_in;
      	c_out <= d | e | f;
      end
endmodule


module rca #(parameter N=4)(input [N-1:0] a,b,  output [N:0] sum);
  wire [N:0] carry;
  wire [N-1 : 0]s;
  assign carry[0] = 1'b0;
   
   genvar i;
   generate 
   for(i=0;i<N;i=i+1)
     begin     	
     	f_a f(a[i], b[i], carry[i], s[i], carry[i+1]);
     end
     endgenerate
   assign sum = {carry[N], s};
endmodule

rca/rca_tb.v
`timescale 1ns / 1ns
module rca_tb;
  reg [3:0]a, b;
  reg c_in;
  wire [4:0]sum;
  rca rca1(.a(a), .b(b), .sum(sum));
           
    initial
        begin
            $dumpfile ("rca_tb.vcd");
            $dumpvars (0, rca_tb);
            #0 a = 4'b0000;
            #0 b = 4'b0001;
            #20 $finish ;
        end
        always #2 a = a + 1'b1;
	always #2 b = b + 1'b1;
endmodule

rca/rca_tb.vcd
$date
	Tue Sep 28 23:42:12 2021
$end
$version
	Icarus Verilog
$end
$timescale
	1ns
$end
$scope module rca_tb $end
$var wire 5 ! sum [4:0] $end
$var reg 4 " a [3:0] $end
$var reg 4 # b [3:0] $end
$scope module rca1 $end
$var wire 4 $ a [3:0] $end
$var wire 4 % b [3:0] $end
$var wire 5 & sum [4:0] $end
$var wire 4 ' s [3:0] $end
$var wire 5 ( carry [4:0] $end
$scope begin genblk1[0] $end
$scope module f $end
$var wire 1 ) a $end
$var wire 1 * b $end
$var wire 1 + c_in $end
$var reg 1 , c_out $end
$var reg 1 - d $end
$var reg 1 . e $end
$var reg 1 / f $end
$var reg 1 0 s $end
$upscope $end
$upscope $end
$scope begin genblk1[1] $end
$scope module f $end
$var wire 1 1 a $end
$var wire 1 2 b $end
$var wire 1 3 c_in $end
$var reg 1 4 c_out $end
$var reg 1 5 d $end
$var reg 1 6 e $end
$var reg 1 7 f $end
$var reg 1 8 s $end
$upscope $end
$upscope $end
$scope begin genblk1[2] $end
$scope module f $end
$var wire 1 9 a $end
$var wire 1 : b $end
$var wire 1 ; c_in $end
$var reg 1 < c_out $end
$var reg 1 = d $end
$var reg 1 > e $end
$var reg 1 ? f $end
$var reg 1 @ s $end
$upscope $end
$upscope $end
$scope begin genblk1[3] $end
$scope module f $end
$var wire 1 A a $end
$var wire 1 B b $end
$var wire 1 C c_in $end
$var reg 1 D c_out $end
$var reg 1 E d $end
$var reg 1 F e $end
$var reg 1 G f $end
$var reg 1 H s $end
$upscope $end
$upscope $end
$upscope $end
$upscope $end
$enddefinitions $end
#0
$dumpvars
0H
0G
0F
0E
0D
0C
0B
0A
0@
0?
0>
0=
0<
0;
0:
09
08
07
06
05
04
03
02
01
10
0/
0.
0-
0,
0+
1*
0)
b0 (
b1 '
b1 &
b1 %
b0 $
b1 #
b0 "
b1 !
$end
#2
b11 !
b11 &
b11 '
18
0*
12
1)
b10 #
b10 %
b1 "
b1 $
#4
1@
1;
b100 (
14
b101 !
b101 &
b101 '
08
15
1*
0)
11
b11 #
b11 %
b10 "
b10 $
#6
0H
0;
0C
04
b0 (
0<
18
05
b111 !
b111 &
b111 '
1@
0>
0*
02
1:
1)
b100 #
b100 %
b11 "
b11 $
#8
1H
1C
b1000 (
1<
08
b1001 !
b1001 &
b1001 '
0@
1=
1*
0)
01
19
b101 #
b101 %
b100 "
b100 $
#10
b1011 !
b1011 &
b1011 '
18
0*
12
1)
b110 #
b110 %
b101 "
b101 $
#12
1@
1?
1>
1;
b1100 (
14
b1101 !
b1101 &
b1101 '
08
15
1*
0)
11
b111 #
b111 %
b110 "
b110 $
#14
0C
0<
0?
0;
04
b0 (
0D
18
05
1@
0>
0=
b1111 !
b1111 &
b1111 '
1H
0F
0*
02
0:
1B
1)
b1000 #
b1000 %
b111 "
b111 $
#16
b10000 (
1D
08
0@
b10001 !
b10001 &
b1 '
0H
1E
1*
0)
01
09
1A
b1001 #
b1001 %
b1000 "
b1000 $
#18
b10011 !
b10011 &
b11 '
18
0*
12
1)
b1010 #
b1010 %
b1001 "
b1001 $
#20
1@
1;
b10100 (
14
b10101 !
b10101 &
b101 '
08
15
1*
0)
11
b1011 #
b1011 %
b1010 "
b1010 $
